topsis/__init__.py
topsis/__main__.py
topsis_rijjwal_102218003-1.0.0.dist-info/LICENSE
topsis_rijjwal_102218003-1.0.0.dist-info/METADATA
topsis_rijjwal_102218003-1.0.0.dist-info/WHEEL
topsis_rijjwal_102218003-1.0.0.dist-info/entry_points.txt
topsis_rijjwal_102218003-1.0.0.dist-info/top_level.txt
topsis_rijjwal_102218003-1.0.0.dist-info/RECORD
